tinydb_constraint/__init__.py
tinydb_constraint/constraint.py
tinydb_constraint/exception.py
tinydb_constraint/table.py
tinydb_constraint/util.py
tinydb_constraint-0.1.8.1.dist-info/LICENSE
tinydb_constraint-0.1.8.1.dist-info/WHEEL
tinydb_constraint-0.1.8.1.dist-info/METADATA
tinydb_constraint-0.1.8.1.dist-info/RECORD
